mathmod/__init__.py
mathmod/area.py
mathmod/fibonacci.py
mathmod/volume.py
mathmod-0.10.4.2.dist-info/LICENSE
mathmod-0.10.4.2.dist-info/METADATA
mathmod-0.10.4.2.dist-info/WHEEL
mathmod-0.10.4.2.dist-info/top_level.txt
mathmod-0.10.4.2.dist-info/RECORD
