Metadata-Version: 2.1
Name: mathmod
Version: 0.10.4.2
Summary: yet another Python math module
Home-page: https://github.com/TheTechRobo/python-text-calculator
Author: TheTechRobo
Author-email: thetechrobo@outlook.com
License: GNU GPL 3.0
Project-URL: Source, https://github.com/thetechrobo/python-text-calculator
Project-URL: Tracker, https://github.com/thetechrobo/python-text-calculator/issues
Keywords: math,easy,thetechrobo
Platform: UNKNOWN
Classifier: Development Status :: 3 - Alpha
Classifier: Intended Audience :: Developers
Classifier: Programming Language :: Python :: 3
Classifier: Programming Language :: Python :: 2
